Workbook
Name CostRatio: Assumptions!$B$8
Name CutA: Assumptions!$B$10
Name CutB: Assumptions!$B$11
Name CutX: Assumptions!$B$12
Name CutY: Assumptions!$B$13
Name HoldingRate: Assumptions!$B$7
Name LeadTime: Assumptions!$B$5
Name OrderCost: Assumptions!$B$6
Name TargetClass: Assumptions!$A$17:$A$19
Name TargetLevel: Assumptions!$B$17:$B$19
Name WeeksPerYear: Assumptions!$B$9

Sheet Summary
A1: Inventory Replenishment Planner
A2: UCI Online Retail II (UK online retailer). Policy set on 2010 demand, tested on Jan-Nov 2011 demand.
A4: 3,937 SKUs sold in 2010; 3,068 of them also sold in 2011 and are in the backtest.
A6: Policy | B6: Class | C6: SKUs | D6: Demand value | E6: Sold value | F6: Fill rate | G6: Stockout SKU-weeks | H6: Avg inventory value | I6: Orders placed | J6: Holding cost | K6: Ordering cost | L6: Total cost
A7: ABC policy | B7: All | C7: =COUNTA(Backtest!$A$5:$A$3072) -> 3068 | D7: =SUM(Backtest!$F$5:$F$3072) -> 7033017.5 | E7: =SUM(Backtest!$I$5:$I$3072) -> 6636292.9 | F7: =E7/D7 -> 0.94359112 | G7: =SUM(Backtest!$K$5:$K$3072) -> 1813 | H7: =SUM(Backtest!$L$5:$L$3072) -> 1197980 | I7: =SUM(Backtest!$M$5:$M$3072) -> 4613 | J7: =H7*HoldingRate*0.923077 -> 276456.94 | K7: =I7*OrderCost -> 115325 | L7: =J7+K7 -> 391781.94
A8: ABC policy | B8: A | C8: =COUNTIFS(Backtest!$C$5:$C$3072,"A") -> 822 | D8: =SUMIFS(Backtest!$F$5:$F$3072,Backtest!$C$5:$C$3072,"A") -> 5479822.7 | E8: =SUMIFS(Backtest!$I$5:$I$3072,Backtest!$C$5:$C$3072,"A") -> 5288764.3 | F8: =E8/D8 -> 0.9651342 | G8: =SUMIFS(Backtest!$K$5:$K$3072,Backtest!$C$5:$C$3072,"A") -> 373 | H8: =SUMIFS(Backtest!$L$5:$L$3072,Backtest!$C$5:$C$3072,"A") -> 742399.18 | I8: =SUMIFS(Backtest!$M$5:$M$3072,Backtest!$C$5:$C$3072,"A") -> 2601 | J8: =H8*HoldingRate*0.923077 -> 171322.9 | K8: =I8*OrderCost -> 65025 | L8: =J8+K8 -> 236347.9
A9: ABC policy | B9: B | C9: =COUNTIFS(Backtest!$C$5:$C$3072,"B") -> 863 | D9: =SUMIFS(Backtest!$F$5:$F$3072,Backtest!$C$5:$C$3072,"B") -> 1024008.9 | E9: =SUMIFS(Backtest!$I$5:$I$3072,Backtest!$C$5:$C$3072,"B") -> 912570.18 | F9: =E9/D9 -> 0.89117411 | G9: =SUMIFS(Backtest!$K$5:$K$3072,Backtest!$C$5:$C$3072,"B") -> 469 | H9: =SUMIFS(Backtest!$L$5:$L$3072,Backtest!$C$5:$C$3072,"B") -> 282843.04 | I9: =SUMIFS(Backtest!$M$5:$M$3072,Backtest!$C$5:$C$3072,"B") -> 1043 | J9: =H9*HoldingRate*0.923077 -> 65271.476 | K9: =I9*OrderCost -> 26075 | L9: =J9+K9 -> 91346.476
A10: ABC policy | B10: C | C10: =COUNTIFS(Backtest!$C$5:$C$3072,"C") -> 1383 | D10: =SUMIFS(Backtest!$F$5:$F$3072,Backtest!$C$5:$C$3072,"C") -> 529185.91 | E10: =SUMIFS(Backtest!$I$5:$I$3072,Backtest!$C$5:$C$3072,"C") -> 434958.35 | F10: =E10/D10 -> 0.82193865 | G10: =SUMIFS(Backtest!$K$5:$K$3072,Backtest!$C$5:$C$3072,"C") -> 971 | H10: =SUMIFS(Backtest!$L$5:$L$3072,Backtest!$C$5:$C$3072,"C") -> 172737.76 | I10: =SUMIFS(Backtest!$M$5:$M$3072,Backtest!$C$5:$C$3072,"C") -> 969 | J10: =H10*HoldingRate*0.923077 -> 39862.563 | K10: =I10*OrderCost -> 24225 | L10: =J10+K10 -> 64087.563
A11: Weeks of cover (4 wk) | B11: All | C11: =COUNTA(Backtest!$A$5:$A$3072) -> 3068 | D11: =SUM(Backtest!$F$5:$F$3072) -> 7033017.5 | E11: =SUM(Backtest!$P$5:$P$3072) -> 6605942.3 | F11: =E11/D11 -> 0.93927568 | G11: =SUM(Backtest!$R$5:$R$3072) -> 1943 | H11: =SUM(Backtest!$S$5:$S$3072) -> 1214986.2 | I11: =SUM(Backtest!$T$5:$T$3072) -> 4569 | J11: =H11*HoldingRate*0.923077 -> 280381.46 | K11: =I11*OrderCost -> 114225 | L11: =J11+K11 -> 394606.46
A12: Weeks of cover (4 wk) | B12: A | C12: =COUNTIFS(Backtest!$C$5:$C$3072,"A") -> 822 | D12: =SUMIFS(Backtest!$F$5:$F$3072,Backtest!$C$5:$C$3072,"A") -> 5479822.7 | E12: =SUMIFS(Backtest!$P$5:$P$3072,Backtest!$C$5:$C$3072,"A") -> 5269881.3 | F12: =E12/D12 -> 0.96168829 | G12: =SUMIFS(Backtest!$R$5:$R$3072,Backtest!$C$5:$C$3072,"A") -> 419 | H12: =SUMIFS(Backtest!$S$5:$S$3072,Backtest!$C$5:$C$3072,"A") -> 770895.02 | I12: =SUMIFS(Backtest!$T$5:$T$3072,Backtest!$C$5:$C$3072,"A") -> 2585 | J12: =H12*HoldingRate*0.923077 -> 177898.87 | K12: =I12*OrderCost -> 64625 | L12: =J12+K12 -> 242523.87
A13: Weeks of cover (4 wk) | B13: B | C13: =COUNTIFS(Backtest!$C$5:$C$3072,"B") -> 863 | D13: =SUMIFS(Backtest!$F$5:$F$3072,Backtest!$C$5:$C$3072,"B") -> 1024008.9 | E13: =SUMIFS(Backtest!$P$5:$P$3072,Backtest!$C$5:$C$3072,"B") -> 903911.7 | F13: =E13/D13 -> 0.88271863 | G13: =SUMIFS(Backtest!$R$5:$R$3072,Backtest!$C$5:$C$3072,"B") -> 515 | H13: =SUMIFS(Backtest!$S$5:$S$3072,Backtest!$C$5:$C$3072,"B") -> 274066.64 | I13: =SUMIFS(Backtest!$T$5:$T$3072,Backtest!$C$5:$C$3072,"B") -> 1031 | J13: =H13*HoldingRate*0.923077 -> 63246.153 | K13: =I13*OrderCost -> 25775 | L13: =J13+K13 -> 89021.153
A14: Weeks of cover (4 wk) | B14: C | C14: =COUNTIFS(Backtest!$C$5:$C$3072,"C") -> 1383 | D14: =SUMIFS(Backtest!$F$5:$F$3072,Backtest!$C$5:$C$3072,"C") -> 529185.91 | E14: =SUMIFS(Backtest!$P$5:$P$3072,Backtest!$C$5:$C$3072,"C") -> 432149.27 | F14: =E14/D14 -> 0.81663034 | G14: =SUMIFS(Backtest!$R$5:$R$3072,Backtest!$C$5:$C$3072,"C") -> 1009 | H14: =SUMIFS(Backtest!$S$5:$S$3072,Backtest!$C$5:$C$3072,"C") -> 170024.57 | I14: =SUMIFS(Backtest!$T$5:$T$3072,Backtest!$C$5:$C$3072,"C") -> 953 | J14: =H14*HoldingRate*0.923077 -> 39236.443 | K14: =I14*OrderCost -> 23825 | L14: =J14+K14 -> 63061.443
A16: Fill rate = share of demand value shipped from stock. Holding cost covers the 48 test weeks.

Sheet Assumptions
A1: Planning assumptions
A2: Yellow cells are inputs. Change one and the SKU Policy, ABC-XYZ and Summary sheets recalculate.
A4: Assumption | B4: Value
A5: Supplier lead time (weeks) | B5: 2
A6: Order cost per purchase order line | B6: 25
A7: Annual holding cost (share of unit cost) | B7: 0.25
A8: Unit cost as share of selling price | B8: 0.6
A9: Weeks per year | B9: 52
A10: Class A cutoff (cumulative revenue share) | B10: 0.8
A11: Class B cutoff (cumulative revenue share) | B11: 0.95
A12: X cutoff (coefficient of variation at or below) | B12: 1
A13: Y cutoff (coefficient of variation at or below) | B13: 2
A15: Cycle service level target by ABC class
A16: Class | B16: Target
A17: A | B17: 0.98
A18: B | B18: 0.95
A19: C | B19: 0.9
A21: Compared against: safety stock of 4 weeks of average demand for every SKU, with the same EOQ order quantities.

Sheet SKU Policy
A1: SKU replenishment policy
A2: One row per SKU sold in 2010, ranked by revenue. Grey columns are 2010 data; the rest are formulas.
A4: Stock code | B4: Description | C4: 2010 revenue | D4: Revenue share | E4: Cumulative share | F4: ABC | G4: Avg price | H4: Unit cost | I4: Avg weekly demand | J4: Weekly std dev | K4: CV | L4: XYZ | M4: Service target | N4: z | O4: Safety stock | P4: Reorder point | Q4: Annual demand | R4: EOQ | S4: Order qty | T4: In 2011 backtest
A5: 22423 | B5: REGENCY CAKESTAND 3 TIER | C5: 179958.84 | D5: =C5/SUM($C$5:$C$3941) -> 0.019523058 | E5: =SUM($C$5:C5)/SUM($C$5:$C$3941) -> 0.019523058 | F5: =IF(E5-D5<CutA,"A",IF(E5-D5<CutB,"B","C")) -> A | G5: 12.551181 | H5: =G5*CostRatio -> 7.5307089 | I5: 275.73077 | J5: 227.04963 | K5: =IF(I5>0,J5/I5,0) -> 0.82344683 | L5: =IF(K5<=CutX,"X",IF(K5<=CutY,"Y","Z")) -> X | M5: =_xlfn.XLOOKUP(F5,TargetClass,TargetLevel) -> 0.98 | N5: =_xlfn.NORM.S.INV(M5) -> 2.0537489 | O5: =N5*J5*SQRT(LeadTime) -> 659.45192 | P5: =ROUNDUP(ROUND(I5*LeadTime+O5,6),0) -> 1211 | Q5: =I5*WeeksPerYear -> 14338 | R5: =SQRT(2*Q5*OrderCost/(HoldingRate*H5)) -> 617.07984 | S5: =MAX(ROUNDUP(ROUND(R5,6),0),ROUNDUP(ROUND(I5,6),0)) -> 618 | T5: Yes
A6: 85123A | B6: WHITE HANGING HEART T-LIGHT HOLDER | C6: 143996.82 | D6: =C6/SUM($C$5:$C$3941) -> 0.015621674 | E6: =SUM($C$5:C6)/SUM($C$5:$C$3941) -> 0.035144731 | F6: =IF(E6-D6<CutA,"A",IF(E6-D6<CutB,"B","C")) -> A | G6: 2.7477687 | H6: =G6*CostRatio -> 1.6486612 | I6: 1007.7885 | J6: 355.15406 | K6: =IF(I6>0,J6/I6,0) -> 0.35240933 | L6: =IF(K6<=CutX,"X",IF(K6<=CutY,"Y","Z")) -> X | M6: =_xlfn.XLOOKUP(F6,TargetClass,TargetLevel) -> 0.98 | N6: =_xlfn.NORM.S.INV(M6) -> 2.0537489 | O6: =N6*J6*SQRT(LeadTime) -> 1031.5235 | P6: =ROUNDUP(ROUND(I6*LeadTime+O6,6),0) -> 3048 | Q6: =I6*WeeksPerYear -> 52405 | R6: =SQRT(2*Q6*OrderCost/(HoldingRate*H6)) -> 2521.3646 | S6: =MAX(ROUNDUP(ROUND(R6,6),0),ROUNDUP(ROUND(I6,6),0)) -> 2522 | T6: Yes
A7: 85099B | B7: JUMBO BAG RED RETROSPOT | C7: 85731.57 | D7: =C7/SUM($C$5:$C$3941) -> 0.0093006957 | E7: =SUM($C$5:C7)/SUM($C$5:$C$3941) -> 0.044445427 | F7: =IF(E7-D7<CutA,"A",IF(E7-D7<CutB,"B","C")) -> A | G7: 1.8190446 | H7: =G7*CostRatio -> 1.0914267 | I7: 906.34615 | J7: 464.38392 | K7: =IF(I7>0,J7/I7,0) -> 0.51236928 | L7: =IF(K7<=CutX,"X",IF(K7<=CutY,"Y","Z")) -> X | M7: =_xlfn.XLOOKUP(F7,TargetClass,TargetLevel) -> 0.98 | N7: =_xlfn.NORM.S.INV(M7) -> 2.0537489 | O7: =N7*J7*SQRT(LeadTime) -> 1348.775 | P7: =ROUNDUP(ROUND(I7*LeadTime+O7,6),0) -> 3162 | Q7: =I7*WeeksPerYear -> 47130 | R7: =SQRT(2*Q7*OrderCost/(HoldingRate*H7)) -> 2938.7756 | S7: =MAX(ROUNDUP(ROUND(R7,6),0),ROUNDUP(ROUND(I7,6),0)) -> 2939 | T7: Yes
A8: 84879 | B8: ASSORTED COLOUR BIRD ORNAMENT | C8: 66096.28 | D8: =C8/SUM($C$5:$C$3941) -> 0.0071705369 | E8: =SUM($C$5:C8)/SUM($C$5:$C$3941) -> 0.051615964 | F8: =IF(E8-D8<CutA,"A",IF(E8-D8<CutB,"B","C")) -> A | G8: 1.6119471 | H8: =G8*CostRatio -> 0.96716828 | I8: 788.53846 | J8: 801.98454 | K8: =IF(I8>0,J8/I8,0) -> 1.0170519 | L8: =IF(K8<=CutX,"X",IF(K8<=CutY,"Y","Z")) -> Y | M8: =_xlfn.XLOOKUP(F8,TargetClass,TargetLevel) -> 0.98 | N8: =_xlfn.NORM.S.INV(M8) -> 2.0537489 | O8: =N8*J8*SQRT(LeadTime) -> 2329.3156 | P8: =ROUNDUP(ROUND(I8*LeadTime+O8,6),0) -> 3907 | Q8: =I8*WeeksPerYear -> 41004 | R8: =SQRT(2*Q8*OrderCost/(HoldingRate*H8)) -> 2911.9042 | S8: =MAX(ROUNDUP(ROUND(R8,6),0),ROUNDUP(ROUND(I8,6),0)) -> 2912 | T8: Yes
A9: 22086 | B9: PAPER CHAIN KIT 50'S CHRISTMAS | C9: 51917.54 | D9: =C9/SUM($C$5:$C$3941) -> 0.0056323387 | E9: =SUM($C$5:C9)/SUM($C$5:$C$3941) -> 0.057248303 | F9: =IF(E9-D9<CutA,"A",IF(E9-D9<CutB,"B","C")) -> A | G9: 3.4973082 | H9: =G9*CostRatio -> 2.0983849 | I9: 285.48077 | J9: 518.16685 | K9: =IF(I9>0,J9/I9,0) -> 1.8150674 | L9: =IF(K9<=CutX,"X",IF(K9<=CutY,"Y","Z")) -> Y | M9: =_xlfn.XLOOKUP(F9,TargetClass,TargetLevel) -> 0.98 | N9: =_xlfn.NORM.S.INV(M9) -> 2.0537489 | O9: =N9*J9*SQRT(LeadTime) -> 1504.9843 | P9: =ROUNDUP(ROUND(I9*LeadTime+O9,6),0) -> 2076 | Q9: =I9*WeeksPerYear -> 14845 | R9: =SQRT(2*Q9*OrderCost/(HoldingRate*H9)) -> 1189.4947 | S9: =MAX(ROUNDUP(ROUND(R9,6),0),ROUNDUP(ROUND(I9,6),0)) -> 1190 | T9: Yes
A10: 47566 | B10: PARTY BUNTING | C10: 49432.29 | D10: =C10/SUM($C$5:$C$3941) -> 0.0053627233 | E10: =SUM($C$5:C10)/SUM($C$5:$C$3941) -> 0.062611026 | F10: =IF(E10-D10<CutA,"A",IF(E10-D10<CutB,"B","C")) -> A | G10: 4.9313937 | H10: =G10*CostRatio -> 2.9588362 | I10: 192.76923 | J10: 204.6596 | K10: =IF(I10>0,J10/I10,0) -> 1.0616819 | L10: =IF(K10<=CutX,"X",IF(K10<=CutY,"Y","Z")) -> Y | M10: =_xlfn.XLOOKUP(F10,TargetClass,TargetLevel) -> 0.98 | N10: =_xlfn.NORM.S.INV(M10) -> 2.0537489 | O10: =N10*J10*SQRT(LeadTime) -> 594.42145 | P10: =ROUNDUP(ROUND(I10*LeadTime+O10,6),0) -> 980 | Q10: =I10*WeeksPerYear -> 10024 | R10: =SQRT(2*Q10*OrderCost/(HoldingRate*H10)) -> 823.14258 | S10: =MAX(ROUNDUP(ROUND(R10,6),0),ROUNDUP(ROUND(I10,6),0)) -> 824 | T10: Yes
A11: 48138 | B11: DOOR MAT UNION FLAG | C11: 43023.1 | D11: =C11/SUM($C$5:$C$3941) -> 0.0046674143 | E11: =SUM($C$5:C11)/SUM($C$5:$C$3941) -> 0.06727844 | F11: =IF(E11-D11<CutA,"A",IF(E11-D11<CutB,"B","C")) -> A | G11: 6.5885299 | H11: =G11*CostRatio -> 3.9531179 | I11: 125.57692 | J11: 85.169346 | K11: =IF(I11>0,J11/I11,0) -> 0.6782245 | L11: =IF(K11<=CutX,"X",IF(K11<=CutY,"Y","Z")) -> X | M11: =_xlfn.XLOOKUP(F11,TargetClass,TargetLevel) -> 0.98 | N11: =_xlfn.NORM.S.INV(M11) -> 2.0537489 | O11: =N11*J11*SQRT(LeadTime) -> 247.36922 | P11: =ROUNDUP(ROUND(I11*LeadTime+O11,6),0) -> 499 | Q11: =I11*WeeksPerYear -> 6530 | R11: =SQRT(2*Q11*OrderCost/(HoldingRate*H11)) -> 574.78007 | S11: =MAX(ROUNDUP(ROUND(R11,6),0),ROUNDUP(ROUND(I11,6),0)) -> 575 | T11: Yes
A12: 21843 | B12: RED RETROSPOT CAKE STAND | C12: 40482.25 | D12: =C12/SUM($C$5:$C$3941) -> 0.0043917671 | E12: =SUM($C$5:C12)/SUM($C$5:$C$3941) -> 0.071670207 | F12: =IF(E12-D12<CutA,"A",IF(E12-D12<CutB,"B","C")) -> A | G12: 10.498509 | H12: =G12*CostRatio -> 6.2991053 | I12: 74.153846 | J12: 55.712281 | K12: =IF(I12>0,J12/I12,0) -> 0.75130669 | L12: =IF(K12<=CutX,"X",IF(K12<=CutY,"Y","Z")) -> X | M12: =_xlfn.XLOOKUP(F12,TargetClass,TargetLevel) -> 0.98 | N12: =_xlfn.NORM.S.INV(M12) -> 2.0537489 | O12: =N12*J12*SQRT(LeadTime) -> 161.81295 | P12: =ROUNDUP(ROUND(I12*LeadTime+O12,6),0) -> 311 | Q12: =I12*WeeksPerYear -> 3856 | R12: =SQRT(2*Q12*OrderCost/(HoldingRate*H12)) -> 349.90011 | S12: =MAX(ROUNDUP(ROUND(R12,6),0),ROUNDUP(ROUND(I12,6),0)) -> 350 | T12: Yes
A13: 20685 | B13: DOOR MAT RED SPOT | C13: 37618.03 | D13: =C13/SUM($C$5:$C$3941) -> 0.0040810386 | E13: =SUM($C$5:C13)/SUM($C$5:$C$3941) -> 0.075751246 | F13: =IF(E13-D13<CutA,"A",IF(E13-D13<CutB,"B","C")) -> A | G13: 6.8471114 | H13: =G13*CostRatio -> 4.1082668 | I13: 105.65385 | J13: 77.225132 | K13: =IF(I13>0,J13/I13,0) -> 0.73092589 | L13: =IF(K13<=CutX,"X",IF(K13<=CutY,"Y","Z")) -> X | M13: =_xlfn.XLOOKUP(F13,TargetClass,TargetLevel) -> 0.98 | N13: =_xlfn.NORM.S.INV(M13) -> 2.0537489 | O13: =N13*J13*SQRT(LeadTime) -> 224.29573 | P13: =ROUNDUP(ROUND(I13*LeadTime+O13,6),0) -> 436 | Q13: =I13*WeeksPerYear -> 5494 | R13: =SQRT(2*Q13*OrderCost/(HoldingRate*H13)) -> 517.16605 | S13: =MAX(ROUNDUP(ROUND(R13,6),0),ROUNDUP(ROUND(I13,6),0)) -> 518 | T13: Yes
A14: 85099F | B14: JUMBO BAG STRAWBERRY | C14: 35522.74 | D14: =C14/SUM($C$5:$C$3941) -> 0.0038537285 | E14: =SUM($C$5:C14)/SUM($C$5:$C$3941) -> 0.079604974 | F14: =IF(E14-D14<CutA,"A",IF(E14-D14<CutB,"B","C")) -> A | G14: 1.8400798 | H14: =G14*CostRatio -> 1.1040479 | I14: 371.25 | J14: 256.67763 | K14: =IF(I14>0,J14/I14,0) -> 0.69138756 | L14: =IF(K14<=CutX,"X",IF(K14<=CutY,"Y","Z")) -> X | M14: =_xlfn.XLOOKUP(F14,TargetClass,TargetLevel) -> 0.98 | N14: =_xlfn.NORM.S.INV(M14) -> 2.0537489 | O14: =N14*J14*SQRT(LeadTime) -> 745.50467 | P14: =ROUNDUP(ROUND(I14*LeadTime+O14,6),0) -> 1489 | Q14: =I14*WeeksPerYear -> 19305 | R14: =SQRT(2*Q14*OrderCost/(HoldingRate*H14)) -> 1870.0618 | S14: =MAX(ROUNDUP(ROUND(R14,6),0),ROUNDUP(ROUND(I14,6),0)) -> 1871 | T14: Yes
A15: 21621 | B15: VINTAGE UNION JACK BUNTING | C15: 35159.84 | D15: =C15/SUM($C$5:$C$3941) -> 0.0038143588 | E15: =SUM($C$5:C15)/SUM($C$5:$C$3941) -> 0.083419333 | F15: =IF(E15-D15<CutA,"A",IF(E15-D15<CutB,"B","C")) -> A | G15: 8.6964729 | H15: =G15*CostRatio -> 5.2178837 | I15: 77.75 | J15: 75.188619 | K15: =IF(I15>0,J15/I15,0) -> 0.96705619 | L15: =IF(K15<=CutX,"X",IF(K15<=CutY,"Y","Z")) -> X | M15: =_xlfn.XLOOKUP(F15,TargetClass,TargetLevel) -> 0.98 | N15: =_xlfn.NORM.S.INV(M15) -> 2.0537489 | O15: =N15*J15*SQRT(LeadTime) -> 218.3808 | P15: =ROUNDUP(ROUND(I15*LeadTime+O15,6),0) -> 374 | Q15: =I15*WeeksPerYear -> 4043 | R15: =SQRT(2*Q15*OrderCost/(HoldingRate*H15)) -> 393.65853 | S15: =MAX(ROUNDUP(ROUND(R15,6),0),ROUNDUP(ROUND(I15,6),0)) -> 394 | T15: Yes
A16: 22386 | B16: JUMBO BAG PINK WITH WHITE SPOTS | C16: 34886.87 | D16: =C16/SUM($C$5:$C$3941) -> 0.0037847453 | E16: =SUM($C$5:C16)/SUM($C$5:$C$3941) -> 0.087204079 | F16: =IF(E16-D16<CutA,"A",IF(E16-D16<CutB,"B","C")) -> A | G16: 1.8896582 | H16: =G16*CostRatio -> 1.1337949 | I16: 355.03846 | J16: 218.99583 | K16: =IF(I16>0,J16/I16,0) -> 0.61682284 | L16: =IF(K16<=CutX,"X",IF(K16<=CutY,"Y","Z")) -> X | M16: =_xlfn.XLOOKUP(F16,TargetClass,TargetLevel) -> 0.98 | N16: =_xlfn.NORM.S.INV(M16) -> 2.0537489 | O16: =N16*J16*SQRT(LeadTime) -> 636.06016 | P16: =ROUNDUP(ROUND(I16*LeadTime+O16,6),0) -> 1347 | Q16: =I16*WeeksPerYear -> 18462 | R16: =SQRT(2*Q16*OrderCost/(HoldingRate*H16)) -> 1804.6256 | S16: =MAX(ROUNDUP(ROUND(R16,6),0),ROUNDUP(ROUND(I16,6),0)) -> 1805 | T16: Yes
... A3941: 84206C | B3941: CHAMPAGNE TRAY BLANK CARD | C3941: 0.19 | D3941: =C3941/SUM($C$5:$C$3941) -> 2.0612386e-08 | E3941: =SUM($C$5:C3941)/SUM($C$5:$C$3941) -> 1 | F3941: =IF(E3941-D3941<CutA,"A",IF(E3941-D3941<CutB,"B","C")) -> C | G3941: 0.19 | H3941: =G3941*CostRatio -> 0.114 | I3941: 0.019230769 | J3941: 0.13867505 | K3941: =IF(I3941>0,J3941/I3941,0) -> 7.2111026 | L3941: =IF(K3941<=CutX,"X",IF(K3941<=CutY,"Y","Z")) -> Z | M3941: =_xlfn.XLOOKUP(F3941,TargetClass,TargetLevel) -> 0.9 | N3941: =_xlfn.NORM.S.INV(M3941) -> 1.2815516 | O3941: =N3941*J3941*SQRT(LeadTime) -> 0.25133294 | P3941: =ROUNDUP(ROUND(I3941*LeadTime+O3941,6),0) -> 1 | Q3941: =I3941*WeeksPerYear -> 1 | R3941: =SQRT(2*Q3941*OrderCost/(HoldingRate*H3941)) -> 41.885391 | S3941: =MAX(ROUNDUP(ROUND(R3941,6),0),ROUNDUP(ROUND(I3941,6),0)) -> 42 | T3941: Yes

Sheet ABC-XYZ
A1: ABC-XYZ matrix
A2: Counts and revenue shares are COUNTIFS / SUMIFS over the SKU Policy sheet.
A4: SKU count | F4: Share of 2010 revenue
B5: X | C5: Y | D5: Z | E5: Total | G5: X | H5: Y | I5: Z | J5: Total
A6: A | B6: =COUNTIFS('SKU Policy'!$F$5:$F$3941,"A",'SKU Policy'!$L$5:$L$3941,"X") -> 268 | C6: =COUNTIFS('SKU Policy'!$F$5:$F$3941,"A",'SKU Policy'!$L$5:$L$3941,"Y") -> 430 | D6: =COUNTIFS('SKU Policy'!$F$5:$F$3941,"A",'SKU Policy'!$L$5:$L$3941,"Z") -> 189 | E6: =SUM(B6:D6) -> 887 | F6: A | G6: =SUMIFS('SKU Policy'!$C$5:$C$3941,'SKU Policy'!$F$5:$F$3941,"A",'SKU Policy'!$L$5:$L$3941,"X")/SUM('SKU Policy'!$C$5:$C$3941) -> 0.34195759 | H6: =SUMIFS('SKU Policy'!$C$5:$C$3941,'SKU Policy'!$F$5:$F$3941,"A",'SKU Policy'!$L$5:$L$3941,"Y")/SUM('SKU Policy'!$C$5:$C$3941) -> 0.34827607 | I6: =SUMIFS('SKU Policy'!$C$5:$C$3941,'SKU Policy'!$F$5:$F$3941,"A",'SKU Policy'!$L$5:$L$3941,"Z")/SUM('SKU Policy'!$C$5:$C$3941) -> 0.10986043 | J6: =SUM(G6:I6) -> 0.80009409
A7: B | B7: =COUNTIFS('SKU Policy'!$F$5:$F$3941,"B",'SKU Policy'!$L$5:$L$3941,"X") -> 81 | C7: =COUNTIFS('SKU Policy'!$F$5:$F$3941,"B",'SKU Policy'!$L$5:$L$3941,"Y") -> 478 | D7: =COUNTIFS('SKU Policy'!$F$5:$F$3941,"B",'SKU Policy'!$L$5:$L$3941,"Z") -> 481 | E7: =SUM(B7:D7) -> 1040 | F7: B | G7: =SUMIFS('SKU Policy'!$C$5:$C$3941,'SKU Policy'!$F$5:$F$3941,"B",'SKU Policy'!$L$5:$L$3941,"X")/SUM('SKU Policy'!$C$5:$C$3941) -> 0.014025123 | H7: =SUMIFS('SKU Policy'!$C$5:$C$3941,'SKU Policy'!$F$5:$F$3941,"B",'SKU Policy'!$L$5:$L$3941,"Y")/SUM('SKU Policy'!$C$5:$C$3941) -> 0.070378877 | I7: =SUMIFS('SKU Policy'!$C$5:$C$3941,'SKU Policy'!$F$5:$F$3941,"B",'SKU Policy'!$L$5:$L$3941,"Z")/SUM('SKU Policy'!$C$5:$C$3941) -> 0.06552847 | J7: =SUM(G7:I7) -> 0.14993247
A8: C | B8: =COUNTIFS('SKU Policy'!$F$5:$F$3941,"C",'SKU Policy'!$L$5:$L$3941,"X") -> 7 | C8: =COUNTIFS('SKU Policy'!$F$5:$F$3941,"C",'SKU Policy'!$L$5:$L$3941,"Y") -> 402 | D8: =COUNTIFS('SKU Policy'!$F$5:$F$3941,"C",'SKU Policy'!$L$5:$L$3941,"Z") -> 1601 | E8: =SUM(B8:D8) -> 2010 | F8: C | G8: =SUMIFS('SKU Policy'!$C$5:$C$3941,'SKU Policy'!$F$5:$F$3941,"C",'SKU Policy'!$L$5:$L$3941,"X")/SUM('SKU Policy'!$C$5:$C$3941) -> 0.00038357805 | H8: =SUMIFS('SKU Policy'!$C$5:$C$3941,'SKU Policy'!$F$5:$F$3941,"C",'SKU Policy'!$L$5:$L$3941,"Y")/SUM('SKU Policy'!$C$5:$C$3941) -> 0.016161932 | I8: =SUMIFS('SKU Policy'!$C$5:$C$3941,'SKU Policy'!$F$5:$F$3941,"C",'SKU Policy'!$L$5:$L$3941,"Z")/SUM('SKU Policy'!$C$5:$C$3941) -> 0.033427927 | J8: =SUM(G8:I8) -> 0.049973437

Sheet Backtest
A1: 2011 backtest by SKU
A2: Each policy replayed week by week against actual Jan-Nov 2011 demand. Unmet demand is a lost sale.
A4: Stock code | B4: Description | C4: ABC | D4: XYZ | E4: Demand units | F4: Demand value | G4: ABC policy: reorder point | H4: ABC policy: order qty | I4: ABC policy: sold value | J4: ABC policy: fill rate | K4: ABC policy: stockout weeks | L4: ABC policy: avg inventory value | M4: ABC policy: orders | N4: Weeks of cover: reorder point | O4: Weeks of cover: order qty | P4: Weeks of cover: sold value | Q4: Weeks of cover: fill rate | R4: Weeks of cover: stockout weeks | S4: Weeks of cover: avg inventory value | T4: Weeks of cover: orders
A5: 22423 | B5: REGENCY CAKESTAND 3 TIER | C5: A | D5: X | E5: 11189 | F5: 140435.17 | G5: 1211 | H5: 618 | I5: 140435.17 | J5: =IF(F5>0,I5/F5,1) -> 1 | K5: 0 | L5: 7860.49 | M5: 18 | N5: 1655 | O5: 618 | P5: 140435.17 | Q5: =IF(F5>0,P5/F5,1) -> 1 | R5: 0 | S5: 11196.6 | T5: 18
A6: 85123A | B6: WHITE HANGING HEART T-LIGHT HOLDER | C6: A | D6: X | E6: 33297 | F6: 91492.46 | G6: 3048 | H6: 2522 | I6: 89439.87 | J6: =IF(F6>0,I6/F6,1) -> 0.97756547 | K6: 1 | L6: 4935.61 | M6: 13 | N6: 6047 | O6: 2522 | P6: 91492.46 | Q6: =IF(F6>0,P6/F6,1) -> 1 | R6: 0 | S6: 9541.94 | T6: 14
A7: 85099B | B7: JUMBO BAG RED RETROSPOT | C7: A | D7: X | E7: 44618 | F7: 81162.13 | G7: 3162 | H7: 2939 | I7: 80561.85 | J7: =IF(F7>0,I7/F7,1) -> 0.99260394 | K7: 1 | L7: 3128.8 | M7: 15 | N7: 5439 | O7: 2939 | P7: 81162.13 | Q7: =IF(F7>0,P7/F7,1) -> 1 | R7: 0 | S7: 5591.47 | T7: 15
A8: 84879 | B8: ASSORTED COLOUR BIRD ORNAMENT | C8: A | D8: Y | E8: 33298 | F8: 53674.62 | G8: 3907 | H8: 2912 | I8: 53008.88 | J8: =IF(F8>0,I8/F8,1) -> 0.98759674 | K8: 1 | L8: 3880.78 | M8: 10 | N8: 4732 | O8: 2912 | P8: 53674.62 | Q8: =IF(F8>0,P8/F8,1) -> 1 | R8: 0 | S8: 4654.58 | T8: 10
A9: 22086 | B9: PAPER CHAIN KIT 50'S CHRISTMAS | C9: A | D9: Y | E9: 14817 | F9: 51819.62 | G9: 2076 | H9: 1190 | I9: 44020.62 | J9: =IF(F9>0,I9/F9,1) -> 0.84949716 | K9: 2 | L9: 4441.89 | M9: 8 | N9: 1713 | O9: 1190 | P9: 42751.1 | Q9: =IF(F9>0,P9/F9,1) -> 0.82499833 | R9: 2 | S9: 3743.65 | T9: 8
A10: 47566 | B10: PARTY BUNTING | C10: A | D10: Y | E10: 17832 | F10: 87936.61 | G10: 980 | H10: 824 | I10: 85732.28 | J10: =IF(F10>0,I10/F10,1) -> 0.97493274 | K10: 3 | L10: 2054.85 | M10: 21 | N10: 1157 | O10: 824 | P10: 86605.14 | Q10: =IF(F10>0,P10/F10,1) -> 0.98485875 | R10: 3 | S10: 2454.42 | T10: 21
A11: 48138 | B11: DOOR MAT UNION FLAG | C11: A | D11: X | E11: 3475 | F11: 22895.14 | G11: 499 | H11: 575 | I11: 22835.84 | J11: =IF(F11>0,I11/F11,1) -> 0.99740993 | K11: 1 | L11: 2560.47 | M11: 6 | N11: 754 | O11: 575 | P11: 22895.14 | Q11: =IF(F11>0,P11/F11,1) -> 1 | R11: 0 | S11: 3597.34 | T11: 6
A12: 21843 | B12: RED RETROSPOT CAKE STAND | C12: A | D12: X | E12: 1507 | F12: 15821.25 | G12: 311 | H12: 350 | I12: 15821.25 | J12: =IF(F12>0,I12/F12,1) -> 1 | K12: 0 | L12: 2714.78 | M12: 4 | N12: 445 | O12: 350 | P12: 15821.25 | Q12: =IF(F12>0,P12/F12,1) -> 1 | R12: 0 | S12: 3565.16 | T12: 4
A13: 20685 | B13: DOOR MAT RED SPOT | C13: A | D13: X | E13: 3576 | F13: 24485.27 | G13: 436 | H13: 518 | I13: 24485.27 | J13: =IF(F13>0,I13/F13,1) -> 1 | K13: 0 | L13: 2271.61 | M13: 7 | N13: 634 | O13: 518 | P13: 24485.27 | Q13: =IF(F13>0,P13/F13,1) -> 1 | R13: 0 | S13: 3085.05 | T13: 7
A14: 85099F | B14: JUMBO BAG STRAWBERRY | C14: A | D14: X | E14: 16351 | F14: 30087.14 | G14: 1489 | H14: 1871 | I14: 30087.14 | J14: =IF(F14>0,I14/F14,1) -> 1 | K14: 0 | L14: 1923.39 | M14: 9 | N14: 2228 | O14: 1871 | P14: 30087.14 | Q14: =IF(F14>0,P14/F14,1) -> 1 | R14: 0 | S14: 2739.28 | T14: 9
A15: 21621 | B15: VINTAGE UNION JACK BUNTING | C15: A | D15: X | E15: 2677 | F15: 23280.46 | G15: 374 | H15: 394 | I15: 23280.46 | J15: =IF(F15>0,I15/F15,1) -> 1 | K15: 0 | L15: 2487.52 | M15: 7 | N15: 467 | O15: 394 | P15: 23280.46 | Q15: =IF(F15>0,P15/F15,1) -> 1 | R15: 0 | S15: 2967.56 | T15: 7
A16: 22386 | B16: JUMBO BAG PINK WITH WHITE SPOTS | C16: A | D16: X | E16: 19913 | F16: 37628.76 | G16: 1347 | H16: 1805 | I16: 37220.6 | J16: =IF(F16>0,I16/F16,1) -> 0.98915298 | K16: 2 | L16: 1595.39 | M16: 11 | N16: 2131 | O16: 1805 | P16: 37628.76 | Q16: =IF(F16>0,P16/F16,1) -> 1 | R16: 0 | S16: 2476 | T16: 11
... A3072: 84206C | B3072: CHAMPAGNE TRAY BLANK CARD | C3072: C | D3072: Z | E3072: 8 | F3072: 1.52 | G3072: 1 | H3072: 42 | I3072: 1.52 | J3072: =IF(F3072>0,I3072/F3072,1) -> 1 | K3072: 0 | L3072: 4.57 | M3072: 0 | N3072: 1 | O3072: 42 | P3072: 1.52 | Q3072: =IF(F3072>0,P3072/F3072,1) -> 1 | R3072: 0 | S3072: 4.57 | T3072: 0

Sheet Trade-off
A1: Service level vs inventory
A2: Each row applies one setting to every SKU and replays 2011 demand. Both methods use the same EOQ order quantities.
A4: Safety stock method | B4: Setting | C4: Fill rate | D4: Avg inventory value | E4: Stockout SKU-weeks | F4: Total cost
A5: Demand variability (service target) | B5: 50% | C5: 0.87696248 | D5: 846958.52 | E5: 3852 | F5: 304076.97
A6: Demand variability (service target) | B6: 70% | C6: 0.90231423 | D6: 937127.82 | E6: 2911 | F6: 327235.27
A7: Demand variability (service target) | B7: 80% | C7: 0.9144978 | D7: 994618.7 | E7: 2516 | F7: 342077.39
A8: Demand variability (service target) | B8: 90% | C8: 0.92939094 | D8: 1075787.5 | E8: 2102 | F8: 362358.65
A9: Demand variability (service target) | B9: 95% | C9: 0.93866233 | D9: 1144833.3 | E9: 1839 | F9: 379367.3
A10: Demand variability (service target) | B10: 98% | C10: 0.94570955 | D10: 1223088.3 | E10: 1612 | F10: 398301.15
A11: Demand variability (service target) | B11: 99% | C11: 0.95017969 | D11: 1274568.5 | E11: 1498 | F11: 410631.2
A12: Demand variability (service target) | B12: 99.5% | C12: 0.95414912 | D12: 1323191.8 | E12: 1381 | F12: 422326.95
A13: Weeks of average demand | B13: 0 wk | C13: 0.87696248 | D13: 846958.52 | E13: 3852 | F13: 304076.97
A14: Weeks of average demand | B14: 1 wk | C14: 0.90086682 | D14: 934759.91 | E14: 3059 | F14: 326213.83
A15: Weeks of average demand | B15: 2 wk | C15: 0.91747723 | D15: 1025571.1 | E15: 2536 | F15: 348995.26
A16: Weeks of average demand | B16: 3 wk | C16: 0.93095551 | D16: 1120387.1 | E16: 2188 | F16: 372050.86
... A19: Weeks of average demand | B19: 8 wk | C19: 0.95877535 | D19: 1604799.4 | E19: 1353 | F19: 486988.33
